{
    "title" : "فرم کوتاه",
    "version": "1",
    "edition": "فرم کوتاه",
    "edition_version": null,
    "filler": "client",
    "description": "## دستور اجرای آزمون\n\nدر این پرسشنامه ۱۳ گروه سوال وجود دارد و هر گروه بیان کننده حالتی در فرد است. عبارت‌های هر گروه را به دقت بخوانید سپس عبارتی را انتخاب کنید که بهتر از همه احساس کنونی شما را بیان می‌کند، یعنی آنچه را که در زمان اجرای تست احساس می‌کنید. سپس دور عدد مقابل آن عبارت را یک دایره بکشید.",
    "prerequisites" : [
        {
            "type" : "text",
            "label" : "gender",
            "text" : "جنسیت",
            "answer" : {
                "type" : "select",
                "options" : [
                    "زن",
                    "مرد"
                ]
            },
            "alias" : "gender",
            "force" : true
        },
        {
            "type": "text",
            "label" : "age",
            "text": "سن",
            "answer": {
                "type": "number"
            },
            "alias" : "age",
            "force": true
        },
        {
            "type": "text",
            "label" : "education",
            "text": "تحصیلات",
            "answer": {
                "type": "select",
                "options" : [
                    "ابتدایی اول",
                    "ابتدایی دوم",
                    "متوسطه اول",
                    "متوسطه دوم",
                    "دیپلم",
                    "کارشناسی",
                    "کارشناسی ارشد",
                    "پزشکی عمومی",
                    "متخصص",
                    "دکتری تخصصی",
                    "حوزوی مقدمات",
                    "حوزوی سطح۱",
                    "حوزوی سطح۲",
                    "حوزوی سطح۳",
                    "حوزوی سطح۴"
                ]
            },
            "alias" : "education",
            "force": true
        }
    ],
    "items": [
        {
            "type": "text",
            "text" : null,
            "answer": {
                "type": "optional",
                "options": [
                    "من آن‌قدر غمگین یا بدبختم که دیگر تحملش را ندارم.",
                    "من همیشه غمگین یا گرفته‌ام‌ و نمی‌توانم خود را از این وضع خلاص کنم.",
                    "من غمگین یا گرفته ام.",
                    "من غمگین نیستم."
                ]
            }
        },
        {
            "type": "text",
            "text" : null,
            "answer": {
                "type": "optional",
                "options": [
                    "من احساس می‌کنم که به آینده امیدی نیست و اوضاع بهتر نخواهد شد.",
                    "من احساس می‌کنم هیچ امیدی به آینده ندارم.",
                    "من نسبت به آینده مایوسم.",
                    "من نسبت به آینده بدبین یا مایوس نیستم."
                ]
            }
        },
        {
            "type": "text",
            "text" : null,
            "answer": {
                "type": "optional",
                "options": [
                    "من احساس می‌کنم شخصی شکست خورده‌ام.",
                    "من هرچه به گذشته‌ام‌ می نگرم چیزی جز شکست نمی‌یابم.",
                    "من احساس می‌کنم بیش از یک شخص متوسط در زندگی با شکست مواجه شده ام.",
                    "من خود را شکست خورده نمی‌دانم."
                ]
            }
        },
        {
            "type": "text",
            "text" : null,
            "answer": {
                "type": "optional",
                "options": [
                    "من از همه چیز ناراضی‌ام.",
                    "دیگر هیچ چیز مرا راضی نمی‌کند.",
                    "من از چیزهایی که لذت می‌بردم، دیگر لذت نمی‌برم.",
                    "من نارضایتی خاصی ندارم."
                ]
            }
        },
        {
            "type": "text",
            "text" : null,
            "answer": {
                "type": "optional",
                "options": [
                    "انگار احساس می‌کنم که بسیار بد یا بی‌ارزش هستم.",
                    ".من احساس می‌کنم که کاملاً گنه کارم",
                    "من اغلب اوقات احساس می‌کنم که بد یا بی‌ارزشم.",
                    "من احساس گنه کاری خاصی ندارم."
                ]
            }
        },
        {
            "type": "text",
            "text" : null,
            "answer": {
                "type": "optional",
                "options": [
                    "من از خودم نفرت دارم.",
                    "من از خودم بیزارم.",
                    "من ازخود ناامیدم.",
                    "من ناامید نیستم"
                ]
            }
        },
        {
            "type": "text",
            "text" : null,
            "answer": {
                "type": "optional",
                "options": [
                    "اگر امکان داشت خود را می‌کشتم.",
                    "من نقشه‌های مشخصی برای خودکشی دارم.",
                    "من احساس می‌کنم که بهتر است بمیرم.",
                    "من به هیچ وجه به فکر آسیب رساندن به خود نیستم."
                ]
            }
        },
        {
            "type": "text",
            "text" : null,
            "answer": {
                "type": "optional",
                "options": [
                    "من تمام علاقه‌ام‌ را نسبت به مردم از دست داده‌ام‌ و به هیچ توجهی به آن‌ها ندارم.",
                    "من علاقه‌ام‌ را تا حد زیادی نسبت به مردم از دست داده‌ام‌ و فقط اندک احساسی نسبت به آن‌ها دارم.",
                    "من اکنون کمتر از گذشته نسبت به مردم علاقه دارم.",
                    "من علاقه‌ام‌ را نسبت به مردم از دست نداده‌ام."
                ]
            }
        },
        {
            "type": "text",
            "text" : null,
            "answer": {
                "type": "optional",
                "options": [
                    "من دیگر نمی‌توانم هیچ تصمیمی بگیرم.",
                    "برای من تصمیم گرفتن مشکل است.",
                    "من سعی می‌کنم تصمیم گیری خود را به تاخیر بیندازنم.",
                    "من مثل همیشه می‌توانم به خوبی تصمیم بگیرم."
                ]
            }
        },
        {
            "type": "text",
            "text" : null,
            "answer": {
                "type": "optional",
                "options": [
                    "من احساس می‌کنم زشت یا زننده‌ام‌.",
                    ".من احساس می‌کنم که وضع ظاهر من دائما در تغییر است و باعث می‌شود در نظر دیگران جذاب نباشم",
                    "من از اینکه پیر یا غیر جذاب به نظر به می‌رسم، نگرانم.",
                    "من احساس نمی‌کنم به نظر دیگران بدتر از گذشته باشم."
                ]
            }
        },
        {
            "type": "text",
            "text" : null,
            "answer": {
                "type": "optional",
                "options": [
                    "من اصلا نمی‌توانم کار کنم.",
                    "من برای انجام هر کاری باید خیلی به خود فشار بیاورم.",
                    "برای من شروع یک کار مستلزم کوششی فوق العاده است.",
                    "من می‌توانم مثل گذشته کار کنم."
                ]
            }
        },
        {
            "type": "text",
            "text" : null,
            "answer": {
                "type": "optional",
                "options": [
                    "من خسته‌تر از آنم که بتوانم کاری انجام دهم.",
                    "من با انجام هر کاری خسته می‌شوم.",
                    "من خیلی زود‌تر از گذشته خسته می‌شوم.",
                    "من بیش از حد معقول خسته نمی‌شوم."
                ]
            }
        },
        {
            "type": "text",
            "text" : null,
            "answer": {
                "type": "optional",
                "options": [
                    "من دیگر به هیچ وجه اشتها ندارم.",
                    "حالا دیگر اشتهای من خیلی بدتر شده است.",
                    "اشتهای من دیگر به خوبی گذشته نیست.",
                    "اشتهای من بد‌تر از حد معمول نیست."
                ]
            }
        }
    ]
}
